{
  "meta": {
    "book": "al-bidayah-wa-al-nihayah",
    "bookArabic": "البداية والنهاية",
    "author": "ibn-kathir",
    "edition": "ط دار ابن كثير",
    "sourceBase": "https://shamela.ws/book/30097",
    "sourceBaseAlt": "https://www.islamweb.net/ar/library/content/59",
    "hijriYear": 358,
    "ceYear": 969,
    "ceSpan": "969",
    "schema": "v3",
    "scope": "ปี ฮ.ศ. 358 (al-Bidayah เล่ม 12, ص248): อาชูรออ์+ทุพภิกขภัยอิรัก+โรมเผาหิมศ์, ★★การพิชิตอียิปต์ของเญาฮัร อัลกออิดให้ฟาฏิมียะฮ์(โดยไม่มีการรบ), ★การเริ่มสร้างเมืองไคโร(อัลกอฮิเราะฮ์) (Rule 89; เล่าตามมุมมองของอิบนุ กะษีร)",
    "groupOrder": [
      "สงครามและภัยพิบัติ",
      "ราชวงศ์ฟาฏิมียะฮ์"
    ],
    "reviewStatus": "DRAFT - แปลตรงจากตำรา (Rule 89)"
  },
  "events": [
    {
      "id": "bidayah-h358-001",
      "cat": "ภัยพิบัติ",
      "group": "สงครามและภัยพิบัติ",
      "order": 1,
      "title": "อาชูรออ์-ฆอดีร, ทุพภิกขภัยรุนแรงในอิรัก และการที่โรมเผาเมืองหิมศ์และจับเชลย ~1 แสนคน",
      "persons": [],
      "places": [
        "baghdad",
        "hims"
      ],
      "accounts": [
        {
          "source": "ibn-kathir",
          "detail": "ในวันอาชูรออ์ พวกรอฟิเฎาะฮ์ได้จัดอุตริกรรม(บิดอะฮ์)ของพวกเขา และในวันฆอดีรคุมก็จัดความรื่นเริงที่อุตริขึ้น และที่อิรักได้เกิดภาวะข้าวยากหมากแพงอย่างรุนแรงจนขนมปังเกือบจะหมดสิ้นไป และพวกโรมได้ก่อความเสียหายในแว่นแคว้นต่างๆ เผาเมืองหิมศ์ ก่อความเสียหายใหญ่หลวงในนั้น และจับเชลยจากบรรดามุสลิมไปราวหนึ่งแสนคน",
          "arabicExcerpt": "في عاشوراء عملت الرَّوافض بدعتهم، وفي يوم غدير خُمّ عملوا الفرح المبتدع. وحصل بالعراق غلاء عظيم حتى كاد يعدم الخبز بالكلية. وعاثت الروم في البلاد فسادًا، وحرقوا حمص، وأفسدوا فيها فسادًا عظيمًا، وسَبَوْا من المسلمين نحوًا من مئة ألف إنسان",
          "loc": "เล่ม 12 หน้า 249",
          "url": "https://shamela.ws/book/30097/5718"
        }
      ],
      "book": "al-bidayah",
      "hijriYear": 358,
      "ceYear": 969,
      "type": "event",
      "confidence": "high",
      "reviewFlags": [
        "Rule 89: แปลตรงเต็มท่อน; ทับศัพท์ขยายความในวงเล็บ"
      ]
    },
    {
      "id": "bidayah-h358-002",
      "cat": "ประวัติศาสตร์",
      "group": "ราชวงศ์ฟาฏิมียะฮ์",
      "order": 2,
      "title": "★★การพิชิตอียิปต์ของเญาฮัร อัลกออิดให้ฟาฏิมียะฮ์ (คุฏบะฮ์นามอัลมุอิซซ์+อะษานแบบชีอะฮ์ โดยไม่มีการรบ)",
      "persons": [
        "jawhar-al-qaid",
        "al-muizz-al-fatimi",
        "kafur-al-ikhshidi"
      ],
      "places": [
        "egypt",
        "ifriqiya"
      ],
      "accounts": [
        {
          "source": "ibn-kathir",
          "detail": "ในปีนี้ อะบุลหะซัน เญาฮัร อัลกออิด อัรรูมีได้ยกกองทัพใหญ่จากฝ่ายอัลมุอิซซ์ ฟาฏิมียะฮ์เข้าสู่ดินแดนอียิปต์ ในวันอังคารที่เหลืออีกสิบสามคืนของเดือนชะอ์บาน ครั้นถึงวันศุกร์ก็มีการอ่านคุฏบะฮ์ในนามอัลมุอิซซ์ ฟาฏิมียะฮ์บนมินบัรทั่วดินแดนอียิปต์และเขตการปกครองทั้งหมด เญาฮัรได้สั่งบรรดามุอัซซินที่มัสยิดญามิอ์อัลอะตีก(มัสยิดอัมร์)และมัสยิดอิบนุ ฏูลูนให้กล่าวในอะษาน(เสียงเรียกละหมาด)ว่า หัยยะ อะลา ค็อยริลอะมัล(จงมาสู่การงานที่ดีที่สุด) และให้บรรดาอิหม่ามอ่านบิสมิลลาฮ์ออกเสียงดัง(ตามแนวทางชีอะฮ์) เนื่องจากเมื่อกาฟูร อัลอิคชีดีเสียชีวิต ที่อียิปต์ไม่มีผู้ใดที่หัวใจของผู้คนจะรวมกันได้ และพวกเขาประสบภาวะข้าวยากหมากแพงอย่างหนักจนอ่อนแอ เมื่อข่าวนั้นถึงอัลมุอิซซ์ขณะอยู่ที่ดินแดนอิฟรีกียะฮ์ เขาจึงส่งเญาฮัร อัลกออิด อัรรูมี ทาสของบิดาเขาคืออัลมันศูร พร้อมกองทัพใหญ่มายังดินแดนอียิปต์ ครั้นข่าวถึงพรรคพวกของกาฟูร พวกเขาก็หนีออกไปก่อนที่เญาฮัรจะมาถึง เญาฮัรจึงเข้ายึดเมืองโดยไม่มีการฟันดาบ การแทง หรือการขัดขวางใดๆ เขาได้ทำสิ่งที่เรากล่าวมา และอำนาจของพวกเขาก็มั่นคงเหนือดินแดนนั้นหลังจากกาฟูร อัลอิคชีดี",
          "arabicExcerpt": "وفيها دخل أبو الحسن جوهر القائد الرُّومي في جيشٍ كثيف من جهة المعز الفاطمي إلى ديار مصر يوم الثلاثاء لثلاث عشرة ليلة بقيت من شعبان، فلما كان يوم الجمعة خطب للمعزِّ الفاطمي على منابر الديار المصرية وسائر أعمالها، وأمر جوهر المؤذنين بالجامع العتيق وبجامع ابن طولون أن يؤذنوا بحي على خير العمل، وأن يجهر الأئمة بالبسملة، وذلك لأنه لما توفي كافور الإخشيدي لم يبق بمصر من تجتمع القلوب عليه، وأصابهم غلاءٌ شديد أضعفهم، فلما بلغ ذلك المُعزّ وهو ببلاد إفريقية بعث جوهر القائد الرومي، مولى أبيه المنصور - في جيش كبير إلى الديار المصرية، فلما بلغ ذلك أصحابَ كافور هربوا منها قبل وصول جوهر القائد إليها، فدخلها آخذًا لها بلا ضربة ولا طعنة ولا ممانعة، ففعل ما ذكرنا من الأمور، واستقرَّت أيديهم على تلك البلاد بعد كافور الإخشيدي",
          "loc": "เล่ม 12 หน้า 249",
          "url": "https://shamela.ws/book/30097/5718"
        }
      ],
      "book": "al-bidayah",
      "hijriYear": 358,
      "ceYear": 969,
      "type": "event",
      "confidence": "high",
      "reviewFlags": [
        "Rule 89: แปลตรงเต็มท่อน; ทับศัพท์ขยายความในวงเล็บ"
      ]
    },
    {
      "id": "bidayah-h358-003",
      "cat": "ประวัติศาสตร์",
      "group": "ราชวงศ์ฟาฏิมียะฮ์",
      "order": 3,
      "title": "★การเริ่มสร้างเมืองอัลกอฮิเราะฮ์(ไคโร)และวังสองหลังโดยเญาฮัร อัลกออิด",
      "persons": [
        "jawhar-al-qaid",
        "al-muizz-al-fatimi"
      ],
      "places": [
        "cairo",
        "egypt"
      ],
      "accounts": [
        {
          "source": "ibn-kathir",
          "detail": "ในปีนี้ เญาฮัร อัลกออิดได้เริ่มสร้างเมืองอัลกอฮิเราะฮ์ อัลมุอิซซียะฮ์(ไคโร) และสร้างวังสองหลังข้างๆ มันดังที่เราจะกล่าวต่อไป และได้จัดเตรียมที่ประทับสำหรับนายของเขาคืออัลมุอิซซ์ ฟาฏิมียะฮ์",
          "arabicExcerpt": "وفي هذه السنة شرع جوهرالقائد في بناء القاهرة المُعزِّية، وبناء القَصْرين عندها على ما سنذكره، وهيأ الإقامات لمولاه المعز الفاطمي",
          "loc": "เล่ม 12 หน้า 249",
          "url": "https://shamela.ws/book/30097/5718"
        }
      ],
      "book": "al-bidayah",
      "hijriYear": 358,
      "ceYear": 969,
      "type": "event",
      "confidence": "high",
      "reviewFlags": [
        "Rule 89: แปลตรงเต็มท่อน; ทับศัพท์ขยายความในวงเล็บ"
      ]
    }
  ]
}
