{
  "meta": {
    "book": "al-bidayah-wa-al-nihayah",
    "bookArabic": "البداية والنهاية",
    "author": "ibn-kathir",
    "edition": "ط دار ابن كثير",
    "sourceBase": "https://shamela.ws/book/30097",
    "sourceBaseAlt": "https://www.islamweb.net/ar/library/content/59",
    "hijriYear": 96,
    "ceYear": 715,
    "ceSpan": "715",
    "schema": "v3",
    "scope": "ปี ฮ.ศ. 96 (เล่ม 14): ยุคอุมัยยะฮ์ - Rule 89 (ทำใหม่แทนโมเดลสรุปเก่า). ★offset vol14: pid=น.+4123★",
    "groupOrder": [
      "เหตุการณ์สำคัญ",
      "การพิชิต (ฟุตูหาต)",
      "ผู้วายชนม์ · ชีวประวัติ"
    ],
    "reviewStatus": "DRAFT - Rule 89 REDO; ปี 96"
  },
  "events": [
    {
      "id": "bidayah-h96-001",
      "book": "al-bidayah",
      "hijriYear": 96,
      "ceYear": 715,
      "order": 1,
      "type": "event",
      "cat": "การเมือง",
      "group": "เหตุการณ์สำคัญ",
      "title": "ปี 96: ★การเสียชีวิตของอัลวะลีดที่ 1 และการขึ้นเป็นเคาะลีฟะฮ์ของสุลัยมาน บิน อับดุลมาลิก★",
      "persons": [
        "al-walid-i",
        "sulayman-b-abd-al-malik",
        "abd-al-malik-b-marwan"
      ],
      "places": [
        "sham"
      ],
      "accounts": [
        {
          "source": "ibn-kathir",
          "detail": "สุลัยมาน(บิน อับดุลมาลิก)ได้รับสัตยาบันเป็นเคาะลีฟะฮ์หลังการเสียชีวิตของอัลวะลีดพี่ชายของเขาในวันที่เขาเสียชีวิต ซึ่งเป็นวันเสาร์กลางเดือนญุมาดัลอาคิเราะฮ์ ปีที่เก้าสิบหก ขณะนั้นสุลัยมานอยู่ที่เมืองอัรร็อมละฮ์",
          "arabicExcerpt": "بويع له بالخلافة بعد موت أخيه الوليد يوم مات، وكان يوم السبت للنصف من جمادى الآخرة سنة ست وتسعين، وكان سليمان بالرَّملة",
          "loc": "เล่ม 14 หน้า 356",
          "url": "https://shamela.ws/book/30097/4479",
          "page": 356
        }
      ],
      "confidence": "high",
      "reviewFlags": []
    }
  ]
}
