{
  "meta": {
    "book": "al-muntazam",
    "bookArabic": "المنتظم في تاريخ الملوك والأمم",
    "author": "ibn-jawzi",
    "edition": "ط دار الكتب العلمية (تحقيق محمد ومصطفى عبد القادر عطا)",
    "sourceBase": "https://shamela.ws/book/12406",
    "sourceBaseAlt": "https://ketabonline.com/ar/books/1326",
    "hijriYear": 5,
    "ceYear": 626,
    "ceSpan": "626 CE",
    "era": "hijri",
    "unit": "hijri-y5",
    "order": 5,
    "schema": "v3",
    "scope": "السنة الخامسة من الهجرة: تمام وفد مزينة وابتداء غزوة المريسيع: ปีที่ห้าแห่งฮิจญ์เราะฮ์ บทสรุปคณะทูตมุซัยนะฮ์ (มุฮาญิรในถิ่นตน คุซาอี) และการเริ่มฆอซวะฮ์อัลมุร็อยซีอ์ (บนีมุศเฏาะลิก) - แปลตรง R89",
    "groupOrder": [
      "AH 5: มุซัยนะฮ์เป็น «มุฮาญิรในถิ่นของตน» และคุซาอี บิน อับดินุฮ์ม (11)",
      "AH 5: เริ่มฆอซวะฮ์อัลมุร็อยซีอ์ (บนีมุศเฏาะลิก) ในชะอ์บาน (12)"
    ],
    "reviewStatus": "DRAFT - AH 5 (muntazam-h5-005, hijriYear=5, era=hijri, unit=hijri-y5); مزينة+بدء المريسيع; แปลตรง (Rule 89); เล่ม 3 (loc=เล่ม 3 หน้า [pid-792])"
  },
  "events": [
    {
      "id": "muntazam-h5-005-001",
      "cat": "สีเราะฮ์",
      "group": "AH 5: มุซัยนะฮ์เป็น «มุฮาญิรในถิ่นของตน» และคุซาอี บิน อับดินุฮ์ม (11)",
      "order": 1,
      "title": "ท่านนบี ﷺ ให้มุซัยนะฮ์คงสถานะมุฮาญิรในถิ่นของตน «กลับไปยังทรัพย์สินของพวกท่าน»; คุซาอี บิน อับดินุฮ์มบัยอะฮ์แทนเผ่า ต่อมาทั้งเผ่าเข้าอิสลาม (1,000 คน) ได้ถือธงมุซัยนะฮ์วันพิชิตมักกะฮ์; พี่น้องอับดุลลอฮ์ ซุลบิญาดัยน์",
      "persons": [
        "prophet-muhammad",
        "khuzai-b-abd-nuhm",
        "abd-allah-dhu-al-bijadayn"
      ],
      "places": [
        "muzayna",
        "medina",
        "mecca"
      ],
      "accounts": [
        {
          "source": "ibn-jawzi",
          "detail": "(คณะทูตมุซัยนะฮ์มาใน) ปีที่ห้า ท่านเราะซูลุลลอฮ์ ﷺ ได้กำหนดให้พวกเขามีสถานะฮิจญ์เราะฮ์ (ผู้อพยพ) ในถิ่นของพวกเขาเอง และกล่าวว่า: «พวกท่านคือผู้อพยพ ณ ที่ใดก็ตามที่พวกท่านอยู่ ดังนั้นจงกลับไปยังทรัพย์สินของพวกท่านเถิด» พวกเขาจึงกลับไปยังดินแดนของตน อิบนุสะอ์ดรายงานจากบรรดาอาจารย์ของเขาว่า ในหมู่พวกเขามีคุซาอี บิน อับดินุฮ์ม เขาได้ให้สัตยาบันต่อท่านเราะซูลุลลอฮ์ ﷺ ในนามของกลุ่มชนของเขาจากมุซัยนะฮ์ เมื่อเขากลับไปหาพวกเขา เขาไม่พบว่าพวกเขาเป็นอย่างที่คิด เขาจึงพำนักอยู่ ต่อมาพวกเขาก็เข้ารับอิสลาม และท่านเราะซูลุลลอฮ์ ﷺ ได้มอบธงของมุซัยนะฮ์ในวันพิชิตมักกะฮ์แก่คุซาอี พวกเขามีจำนวนหนึ่งพันคน และเขาคือพี่น้องของอัลมุฆ็อฟฟัล บิน อับดิลลาฮ์ บิน อัลมุฆ็อฟฟัล และเป็นพี่น้องของอับดุลลอฮ์ ซุลบิญาดัยน์",
          "arabicExcerpt": "سَنَةَ خَمْسٍ، فَجَعَلَ لَهُمْ رَسُولُ اللَّهِ صَلَّى اللَّهُ عَلَيْهِ وَسَلَّمَ الْهِجْرَةَ فِي دَارِهِمْ، وَقَالَ: «أَنْتُمْ مُهَاجِرُونَ حَيْثُ كُنْتُمْ فَارْجِعُوا إِلَى أَمْوَالِكُمْ» فَرَجَعُوا إِلَى بِلادِهِمْ . وروى ابن سعد، عن أشياخه أنه كان فيهم خزاعي بن عبد نهم، وأنه بايع رسول الله صَلَّى اللَّهُ عَلَيْهِ وَسَلَّمَ علي قومه من مزينة، فلما مضى إليهم لم يجدهم كما ظن، / فأقام ثم أنهم أسلموا، ودفع رسول الله صلى الله عليه وسلم لواء مزينة يوم الفتح إلى خزاعي، وكانوا ألف رجل وهو أخو المغفل بن عبد الله بن المغفل، وأخو عبد الله ذي البجادين .",
          "loc": "เล่ม 3 หน้า 218",
          "url": "https://shamela.ws/book/12406/1010",
          "urlAlt": "https://ketabonline.com/ar/books/1326"
        }
      ],
      "book": "al-muntazam",
      "hijriYear": 5,
      "ceYear": 626,
      "era": "hijri",
      "unit": "hijri-y5",
      "type": "event",
      "confidence": "high",
      "reviewFlags": [
        "R89 แปลตรงเต็มท่อน",
        "หุก่ม «مهاجرون حيث كنتم» = ฮิจญ์เราะฮ์เชิงสถานะแม้อยู่ถิ่นเดิม",
        "สายอิบนุสะอ์ด (เฏาะบะกอต)",
        "R92: ﷺ คงสัญลักษณ์"
      ]
    },
    {
      "id": "muntazam-h5-005-002",
      "cat": "สีเราะฮ์",
      "group": "AH 5: เริ่มฆอซวะฮ์อัลมุร็อยซีอ์ (บนีมุศเฏาะลิก) ในชะอ์บาน (12)",
      "order": 2,
      "title": "เริ่มฆอซวะฮ์อัลมุร็อยซีอ์: อัลฮาริษ บิน อบี ฎิรอรหัวหน้าบนีมุศเฏาะลิกระดมพลต้านท่านนบี; ท่านส่งบุร็อยดะฮ์ บิน อัลหุศ็อยบ์สืบข่าว แล้วยกทัพ (ม้า 30 มุนาฟิกีนร่วม) ตั้งซัยด์ บิน หาริษะฮ์รักษาการ ออก 2 ชะอ์บาน",
      "persons": [
        "prophet-muhammad",
        "al-harith-b-abi-dirar",
        "burayda-b-al-husayb",
        "zayd-b-haritha"
      ],
      "places": [
        "al-muraysi",
        "bani-al-mustaliq",
        "medina"
      ],
      "accounts": [
        {
          "source": "ibn-jawzi",
          "detail": "และในปีนี้เกิดฆอซวะฮ์อัลมุร็อยซีอ์ในเดือนชะอ์บาน นั่นคือ บนีมุศเฏาะลิกเคยตั้งถิ่นฐานอยู่ที่บ่อน้ำแห่งหนึ่งของพวกเขาที่เรียกว่าอัลมุร็อยซีอ์ หัวหน้าของพวกเขาคืออัลฮาริษ บิน อบี ฎิรอร เขาได้เดินทางในหมู่กลุ่มชนของเขาและผู้ที่เขารวบรวมได้ เชิญชวนพวกเขาสู่การทำสงครามกับท่านเราะซูลุลลอฮ์ ﷺ พวกเขาก็ตอบรับและเตรียมตัวจะเดินทัพไปกับเขา ข่าวนั้นถึงท่านเราะซูลุลลอฮ์ ﷺ ท่านจึงส่งบุร็อยดะฮ์ บิน อัลหุศ็อยบ์ไปสืบข่าว เขามาถึงพวกเขา พบอัลฮาริษ บิน อบี ฎิรอรและพูดคุยกับเขา แล้วกลับไปหาท่านเราะซูลุลลอฮ์ ﷺ แจ้งให้ทราบ ท่านจึงเรียกระดมผู้คนไปยังพวกเขา พวกเขาก็รีบออกเดินทางพร้อมม้าสามสิบตัว และมีกลุ่มมุนาฟิกีนออกไปด้วย ท่านเราะซูลุลลอฮ์ ﷺ แต่งตั้งซัยด์ บิน หาริษะฮ์รักษาการมะดีนะฮ์ และออกเดินทางในวันจันทร์เมื่อผ่านไปสองคืนของเดือนชะอ์บาน อัลฮาริษ บิน อบี ฎิรอรและผู้ที่อยู่กับเขาได้ทราบข่าวการเดินทัพของท่านเราะซูลุลลอฮ์ ﷺ และทราบว่าท่านได้สังหารสายสืบของเขา (ต่อหน้าถัดไป)",
          "arabicExcerpt": "وفي هذه السنة كانت غزوة المريسيع في شعبان، وذلك أن بني المصطلق كانوا ينزلون على بئر لهم يقال لها: المريسيع، وكان سيدهم الحارث بن أبي ضرار، فسار في قومه ومن قدر عَلَيْهِ فدعاهم إلى حرب رسول الله صلّى الله عليه وسلّم فأجابوه، وتهيأوا للمسير معه، فَبَلَغَ ذَلِكَ رَسُولَ اللَّهِ صَلَّى اللَّهُ عَلَيْهِ وسلم، فبعث بريدة بن الحصيب ليعلم علم ذلك، فأتاهم ولقي الحارث بن أبي ضرار وكلمه ورجع إلى رسول الله صلى الله عليه وسلم، فأخبره، فندب رسول الله صلى الله عليه وسلم الناس إليهم فأسرعوا الخروج ومعهم ثلاثون فرسا، وخرج معهم جماعة من المنافقين، واستخلف رسول الله صلَّى اللَّه عَلَيْهِ وسلم زيد بن حارثة، وخرج يوم الاثنين لليلتين خلتا من شعبان ، وبلغ الحارث بن أبي ضرار ومن معه مسير رسول الله صلى الله عليه وسلم، وأنه قد قتل عينه",
          "loc": "เล่ม 3 หน้า 218",
          "url": "https://shamela.ws/book/12406/1010",
          "urlAlt": "https://ketabonline.com/ar/books/1326"
        }
      ],
      "book": "al-muntazam",
      "hijriYear": 5,
      "ceYear": 626,
      "era": "hijri",
      "unit": "hijri-y5",
      "type": "event",
      "confidence": "high",
      "reviewFlags": [
        "R89 แปลตรงเต็มท่อน (ต่อ pid 1011)",
        "อัลมุร็อยซีอ์ = บ่อน้ำ; ฆอซวะฮ์บนีมุศเฏาะลิก (เชื่อมสู่อัลอิฟก์และเหตุมุนาฟิก)",
        "R92: ﷺ คงสัญลักษณ์"
      ]
    }
  ]
}
