{
  "meta": {
    "book": "al-muntazam",
    "bookArabic": "المنتظم في تاريخ الملوك والأمم",
    "author": "ibn-jawzi",
    "edition": "ط دار الكتب العلمية (تحقيق محمد ومصطفى عبد القادر عطا)",
    "sourceBase": "https://shamela.ws/book/12406",
    "sourceBaseAlt": "https://ketabonline.com/ar/books/1326",
    "hijriYear": null,
    "ceYear": null,
    "ceSpan": null,
    "era": "pre-hijra",
    "unit": "khidr-1",
    "order": 67,
    "schema": "v3",
    "scope": "الخلاف في حياة الخضر: บทถกเถียงเรื่องอายุของอัลเคาะฎิร — คำอ้างว่ายังมีชีวิต (ตาน้ำอมตะ; พบอิลยาสทุกปี; เรื่องเล่าหุบเขาจอร์แดน; นบีที่ยังมีชีวิตสี่ท่าน; อับดาลหกสิบ; เศาะหาบะฮ์ยืนยัน) และการปฏิเสธของอิบนุลเญาซีย์ (สายรายงานอ่อน/ถูกทิ้ง; หนังสือของตน; อิบนุลมุนาดี) - แปลตรง R89",
    "groupOrder": [
      "อัลเคาะฎิร: ยังมีชีวิตหรือไม่"
    ],
    "reviewStatus": "DRAFT - แปลตรงจากตำรา (Rule 89); หน่วยก่อนฮิจญ์เราะฮ์ (era=pre-hijra)"
  },
  "events": [
    {
      "id": "muntazam-pre67-001",
      "cat": "บรรดานบี",
      "group": "อัลเคาะฎิร: ยังมีชีวิตหรือไม่",
      "order": 1,
      "title": "บทถกเถียงเรื่องอายุของอัลเคาะฎิร: คำอ้างว่ายังมีชีวิต (ตาน้ำอมตะ; พบอิลยาสทุกปี; อัลหะสัน อัลบัศรี)",
      "persons": [
        "al-khidr",
        "dhu-al-qarnayn",
        "abd-allah-b-abbas",
        "prophet-muhammad",
        "ilyas-nabi",
        "al-hasan-al-basri"
      ],
      "places": [],
      "accounts": [
        {
          "source": "ibn-jawzi",
          "detail": "ฟัศล์ (บท): บางกลุ่มอ้างว่าอัลเคาะฎิรยังมีชีวิตอยู่จนถึงปัจจุบัน โดยอ้างหะดีษที่ไม่มั่นคงและเรื่องเล่าจากผู้คนที่ใจซื่อ บางคนกล่าวว่า: ฉันได้พบอัลเคาะฎิร ส่วนหะดีษนั้น บางส่วนรายงานจากชาวคัมภีร์ว่า อัลเคาะฎิรอยู่กับซุลก็อรนัยน์ และเขาไปถึงตาน้ำที่ซุลก็อรนัยน์มุ่งหมายก่อน เมื่อมีผู้พรรณนาแก่เขาว่าผู้ใดดื่มจากมันจะเป็นอมตะในดุนยา เขาจึงดื่มและได้รับความเป็นอมตะเพราะเหตุนั้น และบางส่วน (สายรายงาน) จากอิบนุ อับบาส กล่าว ( โดยไม่ทราบว่ายกถึงท่านนบี ﷺ ): \"อัลเคาะฎิรและอิลยาสพบกันทุกปีในฤดูฮัจญ์ ต่างโกนผมให้กัน แล้วแยกจากกันด้วยถ้อยคำเหล่านี้: บิสมิลลาฮ์ มาชาอัลลอฮ์ ไม่มีผู้ใดนำความดีมานอกจากอัลลอฮ์ บิสมิลลาฮ์ มาชาอัลลอฮ์ ไม่มีผู้ใดปัดความชั่วนอกจากอัลลอฮ์ มาชาอัลลอฮ์ ความโปรดปรานใดที่มีก็มาจากอัลลอฮ์ มาชาอัลลอฮ์ ไม่มีพลังและอำนาจใดนอกจากด้วยอัลลอฮ์\" และบางส่วนรายงานจากอัลหะสัน อัลบัศรี ว่าเขากล่าว: อิลยาสถูกมอบหมายดูแลทุ่งร้าง และถูกมอบหมาย",
          "arabicExcerpt": "فصل وَقَدْ زعم قوم أَن الخضر حي إِلَى الآن، واحتجوا بأحاديث لا تثبت وحكايات عَنْ أقوام سليمي الصدور، وَيَقُول أحدهم: لقيت الخضر. فأما الأحاديث: فمنها مَا يروى عَنْ أَهْل الكتاب: أَن الخضر كَانَ مَعَ ذي الْقَرْنَيْنِ، وأنه سبق إِلَى العين الَّتِي قصدها ذو الْقَرْنَيْنِ لما وصف لَهُ أَن من شرب منها خلد فِي الدنيا، فشرب منها فأعطي الخلد لِذَلِكَ. وَمِنْهَا مَا أَخْبَرَنَا بِهِ عَلِيُّ بْنُ أَبِي عُمَرَ الدَّبَّاسُ، قَالَ: أَخْبَرَنَا عَلِيُّ بْنُ الْحُسَيْنِ بْنِ أَيُّوبَ، قَالَ: أَخْبَرَنَا أَبُو عَلِيِّ بْنُ شَاذَانَ، قَالَ: أَخْبَرَنَا إِبْرَاهِيمُ بْنُ مُحَمَّدٍ الْمُزَكِّي، قَالَ: حَدَّثَنَا مُحَمَّدُ بْنُ إِسْحَاقَ بْنِ خُرَيْمٍ، قَالَ: أَخْبَرَنَا مُحَمَّدُ بْنُ أَحْمَدَ بْنِ زَيْدٍ، قَالَ: حَدَّثَنَا عَمْرُو بْنُ عَاصِمٍ، قَالَ: حَدَّثَنَا الحَسَنُ بْنُ رَزِينٍ، عَنِ ابن جريج، عن عطاء، عن ابن عباس، قَالَ: لا أَعْلَمُهُ مَرْفُوعًا إِلَى النَّبِيِّ صَلَّى اللَّهُ عَلَيْهِ وَسَلَّمَ، قَالَ: «يَلْتَقِي الْخَضِرُ وَإِلْيَاسُ فِي كُلِّ عَامٍ فِي الْمَوْسِمِ، فَيَحْلِقُ كُلٌّ مِنْهُمَا عَلَى رَأْسِ صَاحِبِهِ وَيَتَفَرَّقَانِ عَنْ هَؤُلاءِ الْكَلِمَاتِ: «بِسْمِ اللَّهِ، مَا شَاءَ اللَّهُ لا يَسُوقُ الْخَيْرَ إِلا اللَّهُ، بِسْمِ اللَّهِ مَا شَاءَ اللَّهُ لا يَصْرِفُ السُّوءَ إِلا اللَّهُ، مَا شَاءَ اللَّهُ مَا كَانَ مِنْ نِعْمَةٍ فَمِنَ اللَّهِ، مَا شَاءَ اللَّهُ لا حَوْلَ وَلا قُوَّةَ إِلا باللَّه» . ومنها مَا روي عَنِ الْحَسَن البصري، أَنَّهُ، قَالَ: وكل إلياس بالفيافي، ووكل",
          "loc": "เล่ม 1 หน้า 361",
          "url": "https://shamela.ws/book/12406/340",
          "urlAlt": "https://ketabonline.com/ar/books/1326"
        }
      ],
      "book": "al-muntazam",
      "hijriYear": null,
      "ceYear": null,
      "era": "pre-hijra",
      "unit": "khidr-1",
      "type": "event",
      "confidence": "high",
      "reviewFlags": [
        "Rule 89: แปลตรงเต็มท่อน",
        "อิบนุลเญาซีย์อ้างเพื่อจะปฏิเสธ (หะดีษไม่มั่นคง)",
        "ถ้อยคำซิกร์ (มาชาอัลลอฮ์ฯ) ไม่ใช่อัลกุรอาน",
        "notable เท่านั้นลง glossary; ผู้รายงานย่อย/นักวิจารณ์ในสาย ทับศัพท์ในเนื้อ (One)"
      ]
    },
    {
      "id": "muntazam-pre67-002",
      "cat": "บรรดานบี",
      "group": "อัลเคาะฎิร: ยังมีชีวิตหรือไม่",
      "order": 2,
      "title": "เรื่องเล่าพบอิลยาสที่หุบเขาจอร์แดน: นบีที่ยังมีชีวิตสี่ท่าน, อับดาลหกสิบคน และเศาะหาบะฮ์ที่ยืนยัน",
      "persons": [
        "al-khidr",
        "ilyas-nabi",
        "idris-nabi",
        "isa-nabi",
        "prophet-muhammad",
        "ali-b-abi-talib",
        "anas-b-malik",
        "abu-bakr",
        "umar-b-al-khattab",
        "uthman-b-affan",
        "abd-allah-b-umar",
        "umar-ii"
      ],
      "places": [
        "bayt-al-maqdis",
        "arafat",
        "baalbek",
        "egypt",
        "al-furat",
        "antakiya",
        "al-massisa"
      ],
      "accounts": [
        {
          "source": "ibn-jawzi",
          "detail": "อัลเคาะฎิรดูแลทะเลทั้งหลาย และทั้งสองได้รับความเป็นอมตะในดุนยาจนถึงเสียงเป่า ( ศ็อร ) ครั้งแรก และทั้งสองมาพบกันทุกฤดูทุกปี และบางส่วนที่ (สายรายงาน) เล่า จากชายคนหนึ่งที่ประจำการ ( ริบาฏ ) อยู่ในบัยตุลมักดิสและอัสเกาะลาน กล่าวว่า: ขณะที่ฉันเดินอยู่ในหุบเขาจอร์แดน ฉันเห็นชายคนหนึ่งที่ข้างหุบเขายืนละหมาด มีเมฆบังแดดให้เขา ใจฉันรู้สึกว่าเขาคืออิลยาส นบี ฉันจึงเข้าไปให้สลาม เขาเสร็จละหมาดและรับสลาม ฉันถาม: ท่านเป็นใคร ขออัลลอฮ์ทรงเมตตาท่าน? เขาไม่ตอบ ฉันถามซ้ำสองครั้ง เขากล่าว: ฉันคืออิลยาส นบี ฉันตัวสั่นอย่างหนักจนกลัวว่าสติจะหลุด ฉันกล่าวแก่เขา: หากท่านจะกรุณาขอดุอาอ์ให้ฉันหายจากสิ่งที่ฉันเป็นเพื่อให้เข้าใจคำพูดของท่าน เขาขอดุอาอ์ให้ฉันแปดครั้ง กล่าว: ยา บัรร์ ยา เราะฮีม ยา หัย ยา ก็อยยูม ยา หันนาน ยา มันนาน... สิ่งที่ฉันเป็นก็หายไป ฉันถาม: ท่านถูกส่งไปยังใคร? ตอบ: ไปยังชาวบะอ์ลาบัก ฉันถาม: วันนี้ยังมีวะฮีย์มาถึงท่านไหม? ตอบ: นับแต่มุฮัมมัด ﷺ ผู้เป็นตราของบรรดานบีถูกส่งมา ก็ไม่มีอีก ฉันถาม: นบีที่ยังมีชีวิตมีกี่ท่าน? ตอบ: สี่ คือฉันและอัลเคาะฎิรบนแผ่นดิน อิดรีสและอีซาบนฟากฟ้า ฉันถาม: ท่านกับอัลเคาะฎิรพบกันไหม? ตอบ: ใช่ ทุกปีที่อะเราะฟาต ฉันถาม: เรื่องของท่านทั้งสองเป็นอย่างไร? ตอบ: เขาตัดผมของฉันและฉันตัดผมของเขา ฉันถาม: อับดาลมีกี่คน? ตอบ: พวกเขาหกสิบคน ห้าสิบคนอยู่ระหว่างอะรีชแห่งอียิปต์ถึงฝั่งยูเฟรติส สองคนที่อัลมิศศีศะฮ์ สองคนที่อันฏอกียะฮ์ และเจ็ดคนในเมืองอื่นๆ ด้วยพวกเขาฝนจึงตกแก่พวกท่าน ด้วยพวกเขาพวกท่านจึงมีชัยเหนือศัตรู และด้วยพวกเขาอัลลอฮ์ทรงดำรงกิจการของดุนยา จนเมื่อทรงประสงค์จะทำลายดุนยา ก็ทรงให้พวกเขาตายทั้งหมด และมีรายงานว่าเขา ( อัลเคาะฎิร ) อยู่ในสมัยนบีของเรา ﷺ และพวกเขารายงานจากหะดีษอะลีจากท่านนบี ﷺ ยืนยันการมีชีวิตของอัลเคาะฎิร และจากหะดีษอนัส ว่าท่านนบี ﷺ ส่งเขาไปหาอัลเคาะฎิร และกล่าว: จงขอดุอาอ์ให้ศาสนทูตของอัลลอฮ์ และว่าอบู บักร์ อุมัร อุษมาน อะลี และอิบนุ อุมัร ยืนยันการมีอยู่ของเขา และว่าอุมัร บิน อับดุลอะซีซเห็นเขา รายงานโดยมัสละมะฮ์ และริบาห์ บิน อุบัยดะฮ์ ทั้งสองจากอุมัร บิน อับดุลอะซีซ",
          "arabicExcerpt": "الخضر بالبحور، وَقَدْ أعطيا الخلد فِي الدنيا إلى الصيحة الأولى وأنهما يجتمعان في كل موسم فِي كُل عام. ومنها مَا أَخْبَرَنَا بِهِ إِسْحَاق بْن إِبْرَاهِيمَ الختلي، قَالَ: حَدَّثَنِي عُثْمَان بْن سَعِيد الأنطاكي قَالَ: حَدَّثَنَا عَلِي بْن الهيثم المصيصي، عَنْ عَبْد الحميد بْن بحر، عَنْ سلام الطويل، عَنْ دَاوُد بْن يَحْيَى مولى عون الطفاوي، عَنْ رجل كَانَ مرابطا فِي بَيْت المقدس وبعسقلان، قَالَ: بينا أنا أسير فِي وادي الأردن إذا أنا برجل فِي ناحية الوادي قائم يصلي، فَإِذَا سحابة تظله من الشمس فوقع فِي قلبي إنه إلياس النبي صلى الله عليه وسلم، فأتيته فسلمت عَلَيْهِ فانفتل من صلاته فرد عَلِي السَّلام، فَقُلْتُ: من أَنْتَ رحمك اللَّه؟ فلم يرد عَلِي شَيْئًا، فأعدت القول مرتين، فَقَالَ: أَنَا إلياس النَّبِي، فأخذتني رعدة شديدة خشيت عَلَى عقلي أَن يذهب، فَقُلْتُ لَهُ: إِن رأيت رحمك اللَّه أَن تدعو لي أَن يذهب عني مَا أجد حَتَّى أفهم حَدِيثك، فدعا لي بثمان دعوات، فَقَالَ: يا بر يا رحيم، يا حي يا قيوم، يا حنان يا منان،...... ، فَذَهَبَ عني مَا كنت أجد، فَقُلْتُ: إِلَى من بعثت؟ قَالَ: إِلَى أَهْل بعلبك، قُلْت: فهل يوحى إليك اليوم، فَقَالَ: منذ بعث مُحَمَّد صَلَّى اللَّهُ عَلَيْهِ وَسَلَّمَ خاتم النبيين فلا. قُلْتُ: فكم من الأنبياء فِي الحياة؟ قَالَ: أربعة أنا والخضر فِي الأَرْض، وإدريس وعيسى فِي السماء، قُلْت: فهل تلتقي أَنْتَ والخضر؟ قَالَ: نعم فِي كُل عام بعرفات، قُلْت: فَمَا حَدِيثكما؟ قَالَ: يأخذ من شعري وآخذ من شعره، قُلْت: فكم الأبدال؟ قَالَ: هُمْ ستون رجلا، خمسون مَا بَيْنَ عريش مِصْر إِلَى شاطئ الفرات، ورجلان بالمصيصة، ورجلان بأنطاكية، وسبعة فِي سائر الأَمْصَار تسقون بهم الغيث، وبهم ينصرون عَلَى عدوهم، وبهم يقيم اللَّه أمر الدنيا حَتَّى إِذَا أراد أَن يهلك الدنيا أماتهم جميعا. وَقَدْ روي أَنَّهُ كَانَ فِي زمن نبينا صلّى الله عليه وسلم، ورووا من حَدِيث عَلِي عَنِ النَّبِيِّ صَلَّى اللَّهُ عَلَيْهِ وَسَلَّمَ إثبات حياة الخضر. ومن حَدِيث أنس، أن رسول الله صلى الله عليه وَسَلَّمَ بعثه إِلَى الخضر، وَقَالَ: ادع لرسول اللَّه. وإن أبا بَكْر، وَعُمَر، وعثمان، وعليا، وابن عُمَر أثبتوا وجوده، وَإِنَّهُ رآه عُمَر بن عبد العزيز، ورواه مسلمة، ورباح بْن عُبَيْدَة كلاهما عَنْ عُمَر بْن عَبْد العزيز",
          "loc": "เล่ม 1 หน้า 362",
          "url": "https://shamela.ws/book/12406/341",
          "urlAlt": "https://ketabonline.com/ar/books/1326"
        }
      ],
      "book": "al-muntazam",
      "hijriYear": null,
      "ceYear": null,
      "era": "pre-hijra",
      "unit": "khidr-1",
      "type": "event",
      "confidence": "high",
      "reviewFlags": [
        "Rule 89: แปลตรงเต็มท่อน",
        "นบีที่ยังมีชีวิต 4 (อิลยาส/เคาะฎิร/อิดรีส/อีซา) ตามเรื่องเล่า",
        "อับดาล 60; ชื่อเมืองหลายแห่ง",
        "notable เท่านั้นลง glossary; ผู้รายงานย่อย/นักวิจารณ์ในสาย ทับศัพท์ในเนื้อ (One)"
      ]
    },
    {
      "id": "muntazam-pre67-003",
      "cat": "บรรดานบี",
      "group": "อัลเคาะฎิร: ยังมีชีวิตหรือไม่",
      "order": 3,
      "title": "การปฏิเสธของอิบนุลเญาซีย์: สายรายงานอ่อน/ถูกทิ้ง, หนังสือ \"อุญาละตุลมุนตะซ็อร\" และวิจารณ์ของอิบนุลมุนาดี",
      "persons": [
        "al-khidr",
        "ibrahim-b-adham",
        "ahmad-b-hanbal",
        "abd-allah-b-abbas",
        "al-bukhari",
        "al-nasai",
        "al-daraqutni",
        "ibn-hibban",
        "ibn-al-munadi",
        "anas-b-malik",
        "al-dajjal",
        "abu-bakr",
        "umar-b-al-khattab"
      ],
      "places": [],
      "accounts": [
        {
          "source": "ibn-jawzi",
          "detail": "พวกเขากล่าว: และอิบรอฮีม อัตตัยมี อิบรอฮีม บิน อัดฮัม และอะหมัด บิน หันบัล เห็นเขา แต่หะดีษทั้งหมดนี้ไม่มั่นคง หะดีษที่เราเล่าจากอิบนุ อับบาสนั้นมีอัลหะสัน บิน ซัยด์ อยู่ในสาย อัลอุก็อยลีกล่าว: เขาเป็นคนไม่รู้จัก ( มัจญ์ฮูล ) และในหะดีษที่สองมีอัสสะลาม บิน อัฏเฏาะวีล ยะห์ยา ( บิน มะอีน ) กล่าว: เขาไม่มีค่าอะไร อัลบุคอรี อัรรอซี อันนะซาอี และอัดดารุกุฏนีกล่าว: เขาเป็นผู้ถูกทิ้งหะดีษ อิบนุ หิบบานกล่าว: เขารายงานหะดีษกุขึ้นราวกับเป็นหลักของมัน และกล่าว: อับดุลหะมีด บิน บะห์ร์ ไม่อนุญาตให้ใช้อ้างอิงโดยเด็ดขาด ดาวูดเป็นคนไม่รู้จัก และชายที่ประจำการนั้นไม่รู้ว่าเป็นใคร และมัสละมะฮ์ บิน มิศก็อละฮ์รายงานว่าเขาเห็นอิลยาสและเกิดเรื่องกับเขาคล้ายที่ผ่านมา บางทีชัยฏอนปรากฏแก่คนคนหนึ่งและพูดกับเขา และบางทีผู้กล่าวเท็จบางคนกล่าวแก่กันว่า: ฉันคืออัลเคาะฎิร สิ่งที่น่าแปลกที่สุดคือการที่ผู้กล่าวว่า \"ฉันคืออัลเคาะฎิร\" ถูกเชื่อทั้งที่เราไม่มีเครื่องหมายใดที่จะรู้จักเขาได้ ฉันได้รวบรวมหนังสือเล่มหนึ่งชื่อ \"อุญาละตุลมุนตะซ็อร บิชัรห์ ฮาลิลเคาะฎิร\" และกล่าวถึงหะดีษและเรื่องเล่าเหล่านี้และที่คล้ายกัน พร้อมชี้ความผิดพลาดของมัน ฉันจึงไม่เห็นควรยืดยาวในที่นี้ อบุลหุสัยน์ บิน อัลมุนาดีกล่าว และฉันคัดจากลายมือของเขา เกี่ยวกับอายุยืนของอัลเคาะฎิรและว่าเขายังคงอยู่ในดุนยาหรือไม่: ปรากฏว่าคนสะเพร่าส่วนใหญ่ถูกหลอกว่าเขายังอยู่เพราะสิ่งที่ถูกรายงาน เขายกบางส่วนที่เรากล่าวมา แล้วกล่าว: ส่วนหะดีษอนัสนั้นเสียเพราะผู้กุหะดีษ ส่วนรายงานอิบนุ อับบาสอ่อนเพราะอัลหะสัน บิน ร่อซีน ส่วนคำของอัลหุสัยน์รับมาจากผู้ไม่ใช่ชาวศาสนาของเรา ผูกกับคำของบางคนที่ว่าอัลเคาะฎิรดื่มจากตาน้ำที่ซุลก็อรนัยน์มุ่งหมาย ต่อกับที่กล่าวว่าเขาคือชายที่ดัจญาลจะฆ่า และสายที่ถึงเรื่องนั้นถึงชาวซิมมะฮ์ จึงตกไปเพราะความไม่น่าเชื่อถือของพวกเขา ส่วนรายงานมัสละมะฮ์ก็ไม่มีค่า และรายงานริบาห์ก็เหมือนสายลม แล้วอัลลอฮ์ทรงผ่อนต่ออัสสะรีและฎ็อมเราะฮ์ ขออัลลอฮ์ทรงอภัยแก่ทั้งสอง แล้วอัลเคาะฎิรอยู่ไหนตอนแจ้งข่าวดีแก่อบู บักร์และอุมัร เราะฎิยัลลอฮุอันฮุมา เรื่องเคาะลีฟะฮ์ รายงานเหล่านี้อ่อนทั้งต้นและปลาย สภาพของมันไม่พ้นหนึ่งในสองอย่าง: คือ",
          "arabicExcerpt": "قَالُوا: ورآه إِبْرَاهِيم التيمي، وإبراهيم بْن أدهم، وَأَحْمَد بْن حَنْبَل. وكل هذه الأحاديث لا تثبت والحَدِيث الَّذِي ذكرناه عَنِ ابْنِ عَبَّاسٍ فيه الحسن بن زيد، قال العقيلي: هُوَ مجهول. وَفِي الْحَدِيث الثَّانِي السَّلام بْن الطويل، قَالَ يَحْيَى: لَيْسَ بشيء. وَقَالَ الْبُخَارِي، والرازيّ، والنسائي، والدار الدّارقطنيّ: هُوَ متروك الْحَدِيث. وَقَالَ ابْن حيان: يروي الموضوعات كأنه المعتمد لَهَا. قَالَ: وعبد الحميد بْن بحر لا يحل الاحتجاج بِهِ بحال، وَدَاوُد مجهول، والرجل المرابط لا يدري من هُوَ. وَقَدْ رَوَى مسلمة بْن مصقلة، أَنَّهُ رأى إلياس وجرى لَهُ مَعَهُ نَحْو مَا سبق. وربما ظهر الشَّيْطَان لشخص فكلمه، وربما قَالَ بَعْض المتهمين لبعض أنا الخضر، وأعجب الأشياء أَن يصدق القائل أنا الخضر وليس لنا فِيهِ علامة نعرفه بها، وَقَدْ جمعت كتابا سميته عجالة المنتظر بشرح حال الخضر، وذكرت فِيهِ هذه الأحاديث والحكايات ونظائرها وبينت خطأها فلم أر الإطالة بِذَلِكَ هاهنا. قَالَ أَبُو الْحُسَيْن بْن المنادي ونقلته من خطه. ، عَنْ تعمير الخضر وهل هُوَ باق فِي الدنيا أم لا، فَإِذَا أَكْثَر المغفلين مغرورون بأنه باق من أجل مَا قَدْ روي، وساق بَعْض مَا قَدْ ذَكَرْنَا، ثُمَّ قَالَ: أما حَدِيث أَنَس فواه بالوضاع، وَأَمَّا خبر ابْن عَبَّاس فضعيف بالحسن بْن رزين، وَأَمَّا قَوْل الحُسَيْن فمأخوذ عَنْ غَيْر أَهْل ملتنا مربوط بقول بَعْضهم أَن الخضر شرب من العين التي قصدها ذي الْقَرْنَيْنِ موصول بِمَا قيل إنه الرجل الَّذِي يقتله الدجال والمسند من ذلك إلى أهل الذمة فساقط لعدم ثقتهم. وخبر مسلمة فكلا شَيْء، وخبر رياح كالرياح، ثُمَّ مد اللَّه عَلَى السري وضمرة عفى اللَّه عَنْهُمَا. وأين كَانَ الخضر عَنْ تبشير أَبِي بَكْر وعمر رَضِيَ اللَّه عَنْهُمَا بالخلافة. وَهَذِهِ الأخبار واهية الصدور والأعجاز لا تخلو فِي حالها من أحد أمرين: إما",
          "loc": "เล่ม 1 หน้า 363",
          "url": "https://shamela.ws/book/12406/342",
          "urlAlt": "https://ketabonline.com/ar/books/1326"
        }
      ],
      "book": "al-muntazam",
      "hijriYear": null,
      "ceYear": null,
      "era": "pre-hijra",
      "unit": "khidr-1",
      "type": "event",
      "confidence": "high",
      "reviewFlags": [
        "Rule 89: แปลตรงเต็มท่อน",
        "อิบนุลเญาซีย์ชี้สายอ่อน (อัลหะสัน บิน ซัยด์/อัสสะลาม อัฏเฏาะวีล มัจญ์ฮูล/มัตรูก)",
        "อ้างหนังสือของตน + อิบนุลมุนาดี",
        "notable เท่านั้นลง glossary; ผู้รายงานย่อย/นักวิจารณ์ในสาย ทับศัพท์ในเนื้อ (One)"
      ]
    }
  ]
}
