{
  "meta": {
    "book": "al-muntazam",
    "bookArabic": "المنتظم في تاريخ الملوك والأمم",
    "author": "ibn-jawzi",
    "edition": "ط دار الكتب العلمية (تحقيق محمد ومصطفى عبد القادر عطا)",
    "sourceBase": "https://shamela.ws/book/12406",
    "sourceBaseAlt": "https://ketabonline.com/ar/books/1326",
    "hijriYear": 4,
    "ceYear": 625,
    "ceSpan": "625 CE",
    "era": "hijri",
    "unit": "hijri-y4",
    "order": 13,
    "schema": "v3",
    "scope": "السنة الرابعة من الهجرة: وفيات (٧٥-٧٧): ปีที่สี่แห่งฮิจญ์เราะฮ์ หมวดวะฟะยาต #75 หะรอม บิน มิลหาน #76 อัลหะกัม บิน กัยซาน #77 คุบัยบ์ บิน อะดี (ชะฮีดบิอ์รมะอูนะฮ์/อัรเราะญีอ์) - แปลตรง R89",
    "groupOrder": [
      "วะฟะยาต AH 4: #75 หะรอม บิน มิลหาน (ชะฮีดบิอ์รมะอูนะฮ์) (35)",
      "วะฟะยาต AH 4: #76 อัลหะกัม บิน กัยซาน (เมาลาบนีมัคซูม) (36)",
      "วะฟะยาต AH 4: #77 คุบัยบ์ บิน อะดี (สามคำขอ และคำสาปแช่ง) (37)"
    ],
    "reviewStatus": "DRAFT - AH 4 (muntazam-h4-013, hijriYear=4, era=hijri, unit=hijri-y4); وفيات ٧٥-٧٧; แปลตรง (Rule 89); เล่ม 3 (loc=เล่ม 3 หน้า [pid-792])"
  },
  "events": [
    {
      "id": "muntazam-h4-013-001",
      "cat": "สีเราะฮ์",
      "group": "วะฟะยาต AH 4: #75 หะรอม บิน มิลหาน (ชะฮีดบิอ์รมะอูนะฮ์) (35)",
      "order": 1,
      "title": "#75 หะรอม บิน มิลหาน มิลหาน = มาลิก บิน คอลิด บิน ซัยด์: ร่วมบัดร์และอุหุด ชะฮีดที่บิอ์รมะอูนะฮ์",
      "persons": [
        "haram-b-milhan"
      ],
      "places": [
        "badr",
        "uhud",
        "bir-mauna"
      ],
      "accounts": [
        {
          "source": "ibn-jawzi",
          "detail": "๗๕ หะรอม บิน มิลหาน โดยชื่อของมิลหานคือ มาลิก บิน คอลิด บิน ซัยด์: เขาเข้าร่วมบัดร์และอุหุด และถูกสังหารในวันบิอ์รมะอูนะฮ์ในฐานะชะฮีด",
          "arabicExcerpt": "٧٥- حرام بن ملحان، واسم ملحان مالك بن خالد بن زيد : شهد بدرا وأحدا، وقتل يوم بئر معونة شهيدا .",
          "loc": "เล่ม 3 หน้า 209",
          "url": "https://shamela.ws/book/12406/1001",
          "urlAlt": "https://ketabonline.com/ar/books/1326"
        }
      ],
      "book": "al-muntazam",
      "hijriYear": 4,
      "ceYear": 625,
      "era": "hijri",
      "unit": "hijri-y4",
      "type": "event",
      "confidence": "high",
      "reviewFlags": [
        "R89 แปลตรง; วะฟะยาต AH 4",
        "หะรอม บิน มิลหาน = ผู้ถือสาส์นเปิดฉากบิอ์รมะอูนะฮ์ (เทียบ h4-003/004)"
      ]
    },
    {
      "id": "muntazam-h4-013-002",
      "cat": "สีเราะฮ์",
      "group": "วะฟะยาต AH 4: #76 อัลหะกัม บิน กัยซาน (เมาลาบนีมัคซูม) (36)",
      "order": 2,
      "title": "#76 อัลหะกัม บิน กัยซาน: เชลยจากคาราวานนัคละฮ์ อับดุลลอฮ์ บิน ญะห์ช/อัลมิกดาด; ท่านนบี ﷺ อดทนเชิญชวนสู่อิสลามแม้อุมัรจะขอประหาร จนเขาเข้าอิสลามและชะฮีดที่บิอ์รมะอูนะฮ์",
      "persons": [
        "al-hakam-b-kaysan",
        "abd-allah-b-jahsh",
        "al-miqdad",
        "prophet-muhammad",
        "umar-b-al-khattab"
      ],
      "places": [
        "nakhla",
        "bir-mauna",
        "medina"
      ],
      "accounts": [
        {
          "source": "ibn-jawzi",
          "detail": "๗๖ อัลหะกัม บิน กัยซาน เมาลา (ผู้เป็นอิสระในสังกัด) ของบนีมัคซูม: เขาเคยอยู่ในกองคาราวานของกุร็อยช์ที่อับดุลลอฮ์ บิน ญะห์ชโจมตีได้ที่นัคละฮ์ อัลมิกดาดจับเขาเป็นเชลย อับดุลลอฮ์ บิน ญะห์ชต้องการจะตัดคอเขา แต่อัลมิกดาดกล่าวแก่เขาว่: ปล่อยเขาไว้จนกว่าเราจะนำเขาไปหาท่านเราะซูลุลลอฮ์ ﷺ เมื่อพวกเขานำเขามา ท่านเราะซูลุลลอฮ์ ﷺ ก็เริ่มเชิญชวนเขาสู่อิสลามและเชิญชวนอยู่นาน อุมัรกล่าวว่: ท่านจะพูดกับคนนี้ไปทำไม โอ้ท่านเราะซูลุลลอฮ์? ขอสาบานต่ออัลลอฮ์ คนนี้จะไม่มีวันเข้ารับอิสลามตราบชั่วนิรันดร์ ขอให้ฉันตัดคอเขาเถิด เขาจะได้ไปสู่มารดาของเขาคือ (เหว) ฮาวิยะฮ์ (นรก) ท่านเราะซูลุลลอฮ์ ﷺ ก็เริ่มหันไปทางอุมัร แล้วอัลหะกัมก็เข้ารับอิสลาม ต่อสู้ในหนทางของอัลลอฮ์ และถูกสังหารที่บิอ์รมะอูนะฮ์ โดยที่ท่านเราะซูลุลลอฮ์ ﷺ พอพระทัยต่อเขา",
          "arabicExcerpt": "٧٦- الحكم بن كيسان، مولى لبني مخزوم : وكان في عير قريش التي أصابها عبد الله بن جحش بنخلة، فأسره المقداد، وأراد عبد الله بْن جحش ضرب عنقه، فقال له المقداد: دعه حتى نقدم بِهِ عَلَى رَسُولِ اللَّهِ صَلَّى اللَّهُ عَلَيْهِ وسلم، فلما قدموا به جعل رسول الله صَلَّى اللَّهُ عَلَيْهِ وَسَلَّمَ يدعوه إلى الإسلام وأطال دعاءه، فقال عمر: علام تكلم هذا يا رسول اللَّه؟ والله لا يسلم هذا آخر الأبد، دعني أضرب عنقه ، ويقدم إلى أمه الهاوية، فَجَعَلَ رَسُولُ اللَّهِ صَلَّى اللَّهُ عَلَيْهِ وَسَلَّمَ يلتفت إلى عمر وأسلم الحكم، وجاهد وقتل ببئر معونة ورسول الله صلى الله عليه وسلم راض عنه .",
          "loc": "เล่ม 3 หน้า 209",
          "url": "https://shamela.ws/book/12406/1001",
          "urlAlt": "https://ketabonline.com/ar/books/1326"
        }
      ],
      "book": "al-muntazam",
      "hijriYear": 4,
      "ceYear": 625,
      "era": "hijri",
      "unit": "hijri-y4",
      "type": "event",
      "confidence": "high",
      "reviewFlags": [
        "R89 แปลตรงเต็มท่อน",
        "«أمه الهاوية» = สำนวนกุรอาน (อัลกอริอะฮ์ 101:9) หมายถึงนรก",
        "ความอดทนของท่านนบีในการเชิญชวน vs ความเด็ดขาดของอุมัร",
        "R92: ﷺ คงสัญลักษณ์"
      ]
    },
    {
      "id": "muntazam-h4-013-003",
      "cat": "สีเราะฮ์",
      "group": "วะฟะยาต AH 4: #77 คุบัยบ์ บิน อะดี (สามคำขอ และคำสาปแช่ง) (37)",
      "order": 3,
      "title": "#77 คุบัยบ์ บิน อะดี: ร่วมอุหุด ถูกจับที่อัรเราะญีอ์กับซัยด์ บิน อัดดะษินนะฮ์ กักที่บ้านเมาฮับ (ขอสามข้อ) ละหมาดสองร็อกอะฮ์แล้วสาปแช่ง; มุอาวิยะฮ์เล่าว่าอบู สุฟยานหวาดกลัวคำสาปนั้น",
      "persons": [
        "khubayb-b-adi",
        "zayd-b-al-dathinna",
        "mawhab",
        "muawiya",
        "abu-sufyan",
        "prophet-muhammad"
      ],
      "places": [
        "uhud",
        "al-raji",
        "mecca"
      ],
      "accounts": [
        {
          "source": "ibn-jawzi",
          "detail": "๗๗ คุบัยบ์ บิน อะดี บิน มาลิก บิน อามิร บิน มัจญเดะอะฮ์ บิน หัจญ์ญับา: เขาเข้าร่วมอุหุดกับท่านนบี ﷺ และเป็นหนึ่งในผู้ที่ท่านส่งไป (ในคณะที่) บนีลิห์ยาน (ล่อลวง) พวกเขาจับเขากับซัยด์ บิน อัดดะษินนะฮ์เป็นเชลย เขาเคยทำร้ายบางคนของกุร็อยช์ (ในการรบก่อน) พวกเขาจึงกักขังเขาไว้ที่บ้านชายคนหนึ่งชื่อเมาฮับ เขา (คุบัยบ์) กล่าวว่: โอ้เมาฮับ ฉันขอสามข้อจากท่าน คือ ขอให้ท่านให้น้ำจืดฉันดื่ม ขอให้ท่านกันฉันจากสิ่งที่ถูกเชือดพลีบูชาแก่รูปเคารพ และขอให้ท่านแจ้งฉันเมื่อพวกเขาต้องการจะสังหารฉัน จากนั้นพวกเขานำเขาออกไปเพื่อสังหาร เขาจึงละหมาดสองร็อกอะฮ์ก่อนถูกสังหารและวิงวอนสาปแช่งพวกเขาว่า: «ข้าแต่อัลลอฮ์ ขอทรงนับจำนวนพวกเขา และทรงสังหารพวกเขาให้กระจัดกระจาย» มุอาวิยะฮ์ บิน อบี สุฟยานกล่าวว่: แท้จริงฉันได้เห็นอบู สุฟยานผลักฉันลงกับพื้นด้วยความกลัวคำวิงวอนของคุบัยบ์ และผู้คนเคยกล่าวว่า เมื่อชายคนหนึ่งถูกสาปแช่งแล้วเขานอนแนบพื้น คำสาปแช่งก็จะพ้นไปจากเขา ผู้แต่งหนังสือ (อิบนุลเญาซี) กล่าวว่: และเราได้กล่าวถึงวิธีการสังหารคุบัยบ์ไว้แล้วในหมวดเหตุการณ์ (ต่อด้วยอิสนาดในหน้าถัดไป)",
          "arabicExcerpt": "٧٧- خبيب بن عدي بن مالك بن عامر بن مجدعة بن حججبا: شهد أحدا مع النبي صلى الله عليه وسلم، وكان فيمن بعثه مع بني لحيان فأسروه هو وزيد بن الدثنة، فنال من قريش فحبسوه عند رجل يقال له موهب، فقال: يا موهب، أطلب إليك ثلاثا: أن تسقيني العذب، وأن تجنبني ما ذبح على النصب ، وأن تؤذني إذا أرادوا قتلي. ثم أخرجوه ليقتلوه، فصلى ركعتين عند القتل ودعا عليهم، فقال: اللَّهمّ احصهم عددا واقتلهم بددا» . قال معاوية بن أبي سفيان: فلقد رأيت أبا سفيان يلقيني إلى الأرض فرقا/ من دعوة خبيب. وكانوا يقولون إن الرجل إذا دعي عليه فاضطجع زالت عنه الدعوة. قال مؤلف الكتاب: وقد ذكرنا كيفية قتل خبيب في الحوادث. أخبرنا ابن الحصين ، قال: أخبرنا ابن المذهب، قال: أخبرنا ابن جعفر،",
          "loc": "เล่ม 3 หน้า 209",
          "url": "https://shamela.ws/book/12406/1001",
          "urlAlt": "https://ketabonline.com/ar/books/1326"
        }
      ],
      "book": "al-muntazam",
      "hijriYear": 4,
      "ceYear": 625,
      "era": "hijri",
      "unit": "hijri-y4",
      "type": "event",
      "confidence": "high",
      "reviewFlags": [
        "R89 แปลตรงเต็มท่อน",
        "อิบนุลเญาซีอ้างว่ารายละเอียดการสังหารอยู่ในหมวดเหตุการณ์ (h4-006/007)",
        "ความเชื่อพื้นบ้าน: นอนแนบพื้นเลี่ยงคำสาป (บันทึกตามต้นฉบับ)",
        "R92: ﷺ คงสัญลักษณ์"
      ]
    }
  ]
}
